callite/__init__.py
callite/client/__init__.py
callite/client/rpc_client.py
callite/rpctypes/__init__.py
callite/rpctypes/message_base.py
callite/rpctypes/request.py
callite/rpctypes/response.py
callite/rpctypes/rpc_exception.py
callite/server/__init__.py
callite/server/rpc_server.py
callite/shared/__init__.py
callite/shared/redis_connection.py
callite-0.2.9.dist-info/LICENSE
callite-0.2.9.dist-info/METADATA
callite-0.2.9.dist-info/WHEEL
callite-0.2.9.dist-info/RECORD
