Metadata-Version: 2.1
Name: callite
Version: 0.2.9
Summary: Slim Redis RPC implementation
Home-page: https://www.gri.ai
License: MIT
Author: Emrah Gozcu
Author-email: gozcu@gri.ai
Requires-Python: >=3.10,<4.0
Classifier: License :: OSI Approved :: MIT License
Classifier: Programming Language :: Python :: 3
Classifier: Programming Language :: Python :: 3.10
Classifier: Programming Language :: Python :: 3.11
Classifier: Programming Language :: Python :: 3.12
Classifier: Programming Language :: Python :: 3.13
Requires-Dist: redis (>=5.0.3,<6.0.0)
Project-URL: Repository, https://github.com/gri-ai/callite
